xuanxi/__init__.py
xuanxi/server.py
xuanxi-0.3.0.dist-info/METADATA
xuanxi-0.3.0.dist-info/WHEEL
xuanxi-0.3.0.dist-info/entry_points.txt
xuanxi-0.3.0.dist-info/RECORD
