Metadata-Version: 2.4
Name: xuanxi
Version: 0.3.0
Summary: Add your description here
Author-email: 玄穸_621 <2720048423@qq.com>
Requires-Python: >=3.8
Requires-Dist: bs4>=0.0.2
Requires-Dist: dashscope>=1.23.5
Requires-Dist: dotenv>=0.9.9
Requires-Dist: httpx>=0.28.1
Requires-Dist: mcp[cli]>=1.9.4
